update_toml/cli_input_handler.py
update_toml/exceptions/file_not_loaded_exception.py
update_toml/interfaces/input_handler.py
update_toml/main.py
update_toml/models/user_input.py
update_toml/toml_file.py
update_toml-0.2.1.dist-info/METADATA
update_toml-0.2.1.dist-info/WHEEL
update_toml-0.2.1.dist-info/entry_points.txt
update_toml-0.2.1.dist-info/RECORD
